hpolib_extractor/__init__.py
hpolib_extractor/base_extractor.py
hpolib_extractor/hpobench.py
hpolib_extractor/hpolib.py
hpolib_extractor-3.0.1.dist-info/LICENSE
hpolib_extractor-3.0.1.dist-info/METADATA
hpolib_extractor-3.0.1.dist-info/WHEEL
hpolib_extractor-3.0.1.dist-info/top_level.txt
hpolib_extractor-3.0.1.dist-info/RECORD
