Metadata-Version: 2.1
Name: hpolib-extractor
Version: 3.0.1
Home-page: https://github.com/nabenabe0928/hpolib-extractor/
Author: nabenabe0928
Author-email: shuhei.watanabe.utokyo@gmail.com
Platform: Linux
Requires-Python: >=3.8
License-File: LICENSE
Requires-Dist: h5py
Requires-Dist: numpy
Requires-Dist: tqdm
Requires-Dist: pyarrow
Requires-Dist: ujson
